{
    "individualAwards": [
        {
            "id": "overall",
            "awards": [
                {
                    "position": 1,
                    "name": "Rob Danson",
                    "club": "wesham",
                    "seriesRunnerId": 100
                }
            ]
        },
        {
            "id": "f",
            "awards": [
                {
                    "position": 1,
                    "name": "Emily Japp",
                    "club": "blackpool",
                    "seriesRunnerId": 139
                }
            ],
            "sex": "F"
        },
        {
            "id": "v40",
            "awards": [
                {
                    "position": 1,
                    "name": "Rob Affleck",
                    "club": "preston",
                    "seriesRunnerId": 102
                }
            ],
            "ageCategory": "V40"
        },
        {
            "id": "v50",
            "awards": [
                {
                    "position": 1,
                    "name": "John Wright",
                    "club": "blackpool",
                    "seriesRunnerId": 115
                }
            ],
            "ageCategory": "V50"
        },
        {
            "id": "v60",
            "awards": [
                {
                    "position": 1,
                    "name": "John Collier",
                    "club": "wesham",
                    "seriesRunnerId": 157
                }
            ],
            "ageCategory": "V60"
        }
    ],
    "teamAwards": [
        {
            "club": "preston",
            "id": "open"
        },
        {
            "club": "blackpool",
            "id": "ladies"
        },
        {
            "club": "preston",
            "id": "vets"
        },
        {
            "club": "red-rose",
            "id": "vet50"
        },
        {
            "club": "blackpool",
            "id": "vet60"
        }
    ]
}
