{
  "categories": [
    {
      "id": "open",
      "clubs": [
        { "position": 1, "club": "preston", "points": 7, "total": 15, "scorers": [{ "position": 1, "name": "Patrick Brown", "seriesRunnerId": 2 }, { "position": 2, "name": "Alistair Palmer", "seriesRunnerId": 1 }, { "position": 3, "name": "Andy Cottam", "seriesRunnerId": 3 }, { "position": 4, "name": "Tom Brown", "seriesRunnerId": 7 }, { "position": 5, "name": "Darren Mcdermott", "seriesRunnerId": 5 }] },
        { "position": 2, "club": "red-rose", "points": 6, "total": 85, "scorers": [{ "position": 9, "name": "C. Bridge", "seriesRunnerId": 16 }, { "position": 13, "name": "S. Shaw", "seriesRunnerId": 67 }, { "position": 15, "name": "Samantha Edwards", "seriesRunnerId": 68 }, { "position": 18, "name": "P. Butler", "seriesRunnerId": 24 }, { "position": 30, "name": "Paula Plowman", "seriesRunnerId": 47 }] },
        { "position": 3, "club": "blackpool", "points": 5, "total": 88, "scorers": [{ "position": 8, "name": "A. Hall", "seriesRunnerId": 96 }, { "position": 10, "name": "S. Hall", "seriesRunnerId": 97 }, { "position": 22, "name": "C. Bluck", "seriesRunnerId": 41 }, { "position": 23, "name": "J. Hall", "seriesRunnerId": 98 }, { "position": 25, "name": "D. Pickering", "seriesRunnerId": 43 }] },
        { "position": 4, "club": "lytham", "points": 4, "total": 98, "scorers": [{ "position": 6, "name": "Cass Chisholm", "seriesRunnerId": 86 }, { "position": 12, "name": "D. Kirby", "seriesRunnerId": 15 }, { "position": 20, "name": "S. Wise", "seriesRunnerId": 32 }, { "position": 28, "name": "Julia Rolfe", "seriesRunnerId": 49 }, { "position": 32, "name": "P. Hardman", "seriesRunnerId": 92 }] },
        { "position": 5, "club": "thornton", "points": 3, "total": 182, "scorers": [{ "position": 33, "name": "C. Bligh", "seriesRunnerId": 101 }, { "position": 34, "name": "J. Street", "seriesRunnerId": 102 }, { "position": 35, "name": "S. Robinson", "seriesRunnerId": 103 }, { "position": 38, "name": "M. Carey", "seriesRunnerId": 104 }, { "position": 42, "name": "F. Bridge", "seriesRunnerId": 106 }] },
        { "position": 6, "club": "chorley", "points": 2, "total": 76, "scorers": [{ "position": 7, "name": "D. Cowburn", "seriesRunnerId": 95 }, { "position": 14, "name": "P. Bass", "seriesRunnerId": 12 }, { "position": 24, "name": "D. Miller", "seriesRunnerId": 99 }, { "position": 31, "name": "G. Schofield", "seriesRunnerId": 100 }] },
        { "position": 7, "club": "wesham", "points": 1, "total": 63, "scorers": [{ "position": 16, "name": "Steve Myerscough", "seriesRunnerId": 23 }, { "position": 21, "name": "John Collier", "seriesRunnerId": 36 }, { "position": 26, "name": "J. Danson", "seriesRunnerId": 52 }] }
      ]
    },
    {
      "id": "vets",
      "clubs": [
        { "position": 1, "club": "preston", "points": 4, "total": 25, "scorers": [{ "position": 1, "name": "Andy Cottam", "seriesRunnerId": 3 }, { "position": 2, "name": "Darren Mcdermott", "seriesRunnerId": 5 }, { "position": 10, "name": "Steve Bamber", "seriesRunnerId": 19 }, { "position": 12, "name": "Mick Mcloughlin", "seriesRunnerId": 42 }] },
        { "position": 2, "club": "lytham", "points": 3, "total": 43, "scorers": [{ "position": 3, "name": "Cass Chisholm", "seriesRunnerId": 86 }, { "position": 6, "name": "D. Kirby", "seriesRunnerId": 15 }, { "position": 13, "name": "S. Wise", "seriesRunnerId": 32 }, { "position": 21, "name": "Julia Rolfe", "seriesRunnerId": 49 }] },
        { "position": 3, "club": "chorley", "points": 2, "total": 53, "scorers": [{ "position": 4, "name": "D. Cowburn", "seriesRunnerId": 95 }, { "position": 8, "name": "P. Bass", "seriesRunnerId": 12 }, { "position": 17, "name": "D. Miller", "seriesRunnerId": 99 }, { "position": 24, "name": "G. Schofield", "seriesRunnerId": 100 }] },
        { "position": 4, "club": "blackpool", "points": 1, "total": 54, "scorers": [{ "position": 5, "name": "S. Hall", "seriesRunnerId": 97 }, { "position": 15, "name": "C. Bluck", "seriesRunnerId": 41 }, { "position": 16, "name": "J. Hall", "seriesRunnerId": 98 }, { "position": 18, "name": "D. Pickering", "seriesRunnerId": 43 }] },
        { "position": 5, "club": "red-rose", "points": 0, "total": 75, "scorers": [{ "position": 7, "name": "S. Shaw", "seriesRunnerId": 67 }, { "position": 11, "name": "P. Butler", "seriesRunnerId": 24 }, { "position": 23, "name": "Paula Plowman", "seriesRunnerId": 47 }, { "position": 34, "name": "E. Stanier", "seriesRunnerId": 105 }] },
        { "position": 6, "club": "thornton", "points": 0, "total": 112, "scorers": [{ "position": 26, "name": "C. Bligh", "seriesRunnerId": 101 }, { "position": 27, "name": "J. Street", "seriesRunnerId": 102 }, { "position": 28, "name": "S. Robinson", "seriesRunnerId": 103 }, { "position": 31, "name": "M. Carey", "seriesRunnerId": 104 }] },
        { "position": 7, "club": "wesham", "points": 0, "total": 42, "scorers": [{ "position": 9, "name": "Steve Myerscough", "seriesRunnerId": 23 }, { "position": 14, "name": "John Collier", "seriesRunnerId": 36 }, { "position": 19, "name": "J. Danson", "seriesRunnerId": 52 }] }
      ]
    },
    {
      "id": "v50",
      "clubs": [
        { "position": 1, "club": "preston", "points": 3, "total": 15, "scorers": [{ "position": 1, "name": "Darren Mcdermott", "seriesRunnerId": 5 }, { "position": 6, "name": "Steve Bamber", "seriesRunnerId": 19 }, { "position": 8, "name": "Mick Mcloughlin", "seriesRunnerId": 42 }] },
        { "position": 2, "club": "chorley", "points": 2, "total": 17, "scorers": [{ "position": 2, "name": "D. Cowburn", "seriesRunnerId": 95 }, { "position": 4, "name": "P. Bass", "seriesRunnerId": 12 }, { "position": 11, "name": "D. Miller", "seriesRunnerId": 99 }] },
        { "position": 3, "club": "red-rose", "points": 1, "total": 27, "scorers": [{ "position": 3, "name": "S. Shaw", "seriesRunnerId": 67 }, { "position": 7, "name": "P. Butler", "seriesRunnerId": 24 }, { "position": 17, "name": "Paula Plowman", "seriesRunnerId": 47 }] },
        { "position": 4, "club": "wesham", "points": 0, "total": 28, "scorers": [{ "position": 5, "name": "Steve Myerscough", "seriesRunnerId": 23 }, { "position": 10, "name": "John Collier", "seriesRunnerId": 36 }, { "position": 13, "name": "J. Danson", "seriesRunnerId": 52 }] },
        { "position": 5, "club": "blackpool", "points": 0, "total": 42, "scorers": [{ "position": 12, "name": "D. Pickering", "seriesRunnerId": 43 }, { "position": 14, "name": "L. Lawler", "seriesRunnerId": 73 }, { "position": 16, "name": "Simon Scarr", "seriesRunnerId": 50 }] },
        { "position": 6, "club": "lytham", "points": 0, "total": 43, "scorers": [{ "position": 9, "name": "S. Wise", "seriesRunnerId": 32 }, { "position": 15, "name": "Julia Rolfe", "seriesRunnerId": 49 }, { "position": 19, "name": "P. Hardman", "seriesRunnerId": 92 }] },
        { "position": 7, "club": "thornton", "points": 0, "total": 63, "scorers": [{ "position": 20, "name": "C. Bligh", "seriesRunnerId": 101 }, { "position": 21, "name": "J. Street", "seriesRunnerId": 102 }, { "position": 22, "name": "S. Robinson", "seriesRunnerId": 103 }] }
      ]
    },
    {
      "id": "v60",
      "clubs": [
        { "position": 1, "club": "red-rose", "points": 2, "total": 4, "scorers": [{ "position": 1, "name": "S. Shaw", "seriesRunnerId": 67 }, { "position": 3, "name": "P. Butler", "seriesRunnerId": 24 }] },
        { "position": 2, "club": "preston", "points": 1, "total": 6, "scorers": [{ "position": 2, "name": "Steve Bamber", "seriesRunnerId": 19 }, { "position": 4, "name": "Mick Mcloughlin", "seriesRunnerId": 42 }] },
        { "position": 3, "club": "lytham", "points": 0, "total": 14, "scorers": [{ "position": 5, "name": "S. Wise", "seriesRunnerId": 32 }, { "position": 9, "name": "Julia Rolfe", "seriesRunnerId": 49 }] },
        { "position": 4, "club": "blackpool", "points": 0, "total": 18, "scorers": [{ "position": 8, "name": "D. Pickering", "seriesRunnerId": 43 }, { "position": 10, "name": "Simon Scarr", "seriesRunnerId": 50 }] },
        { "position": 5, "club": "chorley", "points": 0, "total": 19, "scorers": [{ "position": 7, "name": "D. Miller", "seriesRunnerId": 99 }, { "position": 12, "name": "G. Schofield", "seriesRunnerId": 100 }] },
        { "position": 6, "club": "thornton", "points": 0, "total": 29, "scorers": [{ "position": 14, "name": "C. Bligh", "seriesRunnerId": 101 }, { "position": 15, "name": "S. Robinson", "seriesRunnerId": 103 }] },
        { "position": 7, "club": "wesham", "points": 0, "total": 6, "scorers": [{ "position": 6, "name": "John Collier", "seriesRunnerId": 36 }] }
      ]
    },
    {
      "id": "ladies",
      "clubs": [
        { "position": 1, "club": "lytham", "points": 3, "total": 13, "scorers": [{ "position": 1, "name": "Cass Chisholm", "seriesRunnerId": 86 }, { "position": 5, "name": "Julia Rolfe", "seriesRunnerId": 49 }, { "position": 7, "name": "P. Hardman", "seriesRunnerId": 92 }] },
        { "position": 2, "club": "red-rose", "points": 2, "total": 18, "scorers": [{ "position": 2, "name": "Samantha Edwards", "seriesRunnerId": 68 }, { "position": 6, "name": "Paula Plowman", "seriesRunnerId": 47 }, { "position": 10, "name": "E. Stanier", "seriesRunnerId": 105 }] },
        { "position": 3, "club": "blackpool", "points": 1, "total": 20, "scorers": [{ "position": 3, "name": "J. Hall", "seriesRunnerId": 98 }, { "position": 4, "name": "L. Lawler", "seriesRunnerId": 73 }, { "position": 13, "name": "L. Bluck", "seriesRunnerId": 55 }] },
        { "position": 4, "club": "thornton", "points": 0, "total": 37, "scorers": [{ "position": 11, "name": "F. Bridge", "seriesRunnerId": 106 }, { "position": 12, "name": "D. Jackson", "seriesRunnerId": 107 }, { "position": 14, "name": "D. Saunders", "seriesRunnerId": 108 }] },
        { "position": 5, "club": "preston", "points": 0, "total": 25, "scorers": [{ "position": 9, "name": "Olga Wiggins", "seriesRunnerId": 53 }, { "position": 16, "name": "Charlotte Gregory", "seriesRunnerId": 111 }] },
        { "position": 6, "club": "chorley", "points": 0, "total": 0, "scorers": [] },
        { "position": 7, "club": "thornton", "points": 0, "total": 0, "scorers": [] }
      ]
    }
  ]
}
