[
  {
    "id": 100,
    "firstName": "Charlie",
    "lastName": "Pass",
    "club": "wesham",
    "sex": "M",
    "ageCategory": "SEN",
    "runnerId": 13166
  },
  {
    "id": 101,
    "firstName": "Darren",
    "lastName": "McDermott",
    "club": "preston",
    "sex": "M",
    "ageCategory": "V40",
    "runnerId": 10485
  },
  {
    "id": 102,
    "firstName": "Nichola",
    "lastName": "Jackson",
    "club": "preston",
    "sex": "F",
    "ageCategory": "SEN",
    "runnerId": 12268
  },
  {
    "id": 103,
    "firstName": "John",
    "lastName": "Griffiths",
    "club": "preston",
    "sex": "M",
    "ageCategory": "V40",
    "runnerId": 10809
  },
  {
    "id": 104,
    "firstName": "Kingsley",
    "lastName": "Judd",
    "club": "preston",
    "sex": "M",
    "ageCategory": "JUN",
    "runnerId": 12878
  },
  {
    "id": 105,
    "firstName": "Gary",
    "lastName": "Johnstone",
    "club": "blackpool",
    "sex": "M",
    "ageCategory": "V50",
    "runnerId": 13971
  },
  {
    "id": 106,
    "firstName": "Gary",
    "lastName": "Moore",
    "club": "wesham",
    "sex": "M",
    "ageCategory": "V50",
    "runnerId": 12151
  },
  {
    "id": 107,
    "firstName": "Chris",
    "lastName": "Whitlock",
    "club": "wesham",
    "sex": "M",
    "ageCategory": "V40",
    "runnerId": 13139
  },
  {
    "id": 108,
    "firstName": "Sarah",
    "lastName": "Sherratt",
    "club": "wesham",
    "sex": "F",
    "ageCategory": "SEN",
    "runnerId": 11231
  },
  {
    "id": 109,
    "firstName": "Philip",
    "lastName": "Butler",
    "club": "red-rose",
    "sex": "M",
    "ageCategory": "V40",
    "runnerId": 10482
  },
  {
    "id": 110,
    "firstName": "Mark",
    "lastName": "Midgley",
    "club": "wesham",
    "sex": "M",
    "ageCategory": "V40",
    "runnerId": 12989
  },
  {
    "id": 111,
    "firstName": "Simon",
    "lastName": "Townsend",
    "club": "chorley-ac",
    "sex": "M",
    "ageCategory": "V40",
    "runnerId": 10395
  },
  {
    "id": 112,
    "firstName": "Dave",
    "lastName": "Kershaw",
    "club": "chorley-ac",
    "sex": "M",
    "ageCategory": "V50",
    "runnerId": 11757
  },
  {
    "id": 113,
    "firstName": "Lindsey",
    "lastName": "Berends",
    "club": "preston",
    "sex": "F",
    "ageCategory": "SEN",
    "runnerId": 12484
  },
  {
    "id": 114,
    "firstName": "Stuart",
    "lastName": "Tunney",
    "club": "chorley-ac",
    "sex": "M",
    "ageCategory": "SEN",
    "runnerId": 13972
  },
  {
    "id": 115,
    "firstName": "Shane",
    "lastName": "Cliffe",
    "club": "red-rose",
    "sex": "M",
    "ageCategory": "V40",
    "runnerId": 10955
  },
  {
    "id": 116,
    "firstName": "Melanie",
    "lastName": "Koth",
    "club": "lytham",
    "sex": "F",
    "ageCategory": "SEN",
    "runnerId": 10167
  },
  {
    "id": 117,
    "firstName": "Mark",
    "lastName": "Willett",
    "club": "lytham",
    "sex": "M",
    "ageCategory": "SEN",
    "runnerId": 12642
  },
  {
    "id": 118,
    "firstName": "Barry",
    "lastName": "Wheeler",
    "club": "red-rose",
    "sex": "M",
    "ageCategory": "SEN",
    "runnerId": 10123
  },
  {
    "id": 119,
    "firstName": "John",
    "lastName": "Rogerson",
    "club": "red-rose",
    "sex": "M",
    "ageCategory": "V50",
    "runnerId": 12965
  },
  {
    "id": 120,
    "firstName": "Peter",
    "lastName": "Bolton",
    "club": "red-rose",
    "sex": "M",
    "ageCategory": "V50",
    "runnerId": 10860
  },
  {
    "id": 121,
    "firstName": "William",
    "lastName": "Johnstone",
    "club": "preston",
    "sex": "M",
    "ageCategory": "V40",
    "runnerId": 10635
  },
  {
    "id": 122,
    "firstName": "Claire",
    "lastName": "McDermott",
    "club": "preston",
    "sex": "F",
    "ageCategory": "V40",
    "runnerId": 11084
  },
  {
    "id": 123,
    "firstName": "Henry",
    "lastName": "Minorczyk",
    "club": "chorley-ac",
    "sex": "M",
    "ageCategory": "V60",
    "runnerId": 11526
  },
  {
    "id": 124,
    "firstName": "Jeffrey",
    "lastName": "Wright",
    "club": "blackpool",
    "sex": "M",
    "ageCategory": "V50",
    "runnerId": 12023
  },
  {
    "id": 125,
    "firstName": "Jenny",
    "lastName": "Salt",
    "club": "wesham",
    "sex": "F",
    "ageCategory": "SEN",
    "runnerId": 10241
  },
  {
    "id": 126,
    "firstName": "Paul",
    "lastName": "Wareing",
    "club": "chorley-ac",
    "sex": "M",
    "ageCategory": "V40",
    "runnerId": 10118
  },
  {
    "id": 127,
    "firstName": "Ian",
    "lastName": "France",
    "club": "wesham",
    "sex": "M",
    "ageCategory": "V40",
    "runnerId": 13973
  },
  {
    "id": 128,
    "firstName": "Nigel",
    "lastName": "Shepherd",
    "club": "wesham",
    "sex": "M",
    "ageCategory": "V50",
    "runnerId": 10146
  },
  {
    "id": 129,
    "firstName": "Glenda",
    "lastName": "Dobie",
    "club": "red-rose",
    "sex": "F",
    "ageCategory": "V50",
    "runnerId": 13056
  },
  {
    "id": 130,
    "firstName": "Steve",
    "lastName": "Coey",
    "club": "red-rose",
    "sex": "M",
    "ageCategory": "V50",
    "runnerId": 12796
  },
  {
    "id": 131,
    "firstName": "Debbie",
    "lastName": "Cooper",
    "club": "lytham",
    "sex": "F",
    "ageCategory": "SEN",
    "runnerId": 11514
  },
  {
    "id": 132,
    "firstName": "Barry",
    "lastName": "Chester",
    "club": "chorley-ac",
    "sex": "M",
    "ageCategory": "V60",
    "runnerId": 13037
  },
  {
    "id": 133,
    "firstName": "Pete",
    "lastName": "McDermott",
    "club": "preston",
    "sex": "M",
    "ageCategory": "V60",
    "runnerId": 10847
  },
  {
    "id": 134,
    "firstName": "Peter",
    "lastName": "Gibson",
    "club": "blackpool",
    "sex": "M",
    "ageCategory": "V50",
    "runnerId": 11341
  },
  {
    "id": 135,
    "firstName": "Sally",
    "lastName": "Cape",
    "club": "red-rose",
    "sex": "F",
    "ageCategory": "V40",
    "runnerId": 12162
  },
  {
    "id": 136,
    "firstName": "John",
    "lastName": "Minton",
    "club": "chorley-ac",
    "sex": "M",
    "ageCategory": "V70",
    "runnerId": 12818
  },
  {
    "id": 137,
    "firstName": "Dave",
    "lastName": "Roberts",
    "club": "preston",
    "sex": "M",
    "ageCategory": "V60",
    "runnerId": 11873
  },
  {
    "id": 138,
    "firstName": "Melanie",
    "lastName": "Haworth",
    "club": "preston",
    "sex": "F",
    "ageCategory": "SEN",
    "runnerId": 12305
  },
  {
    "id": 139,
    "firstName": "George",
    "lastName": "Fletcher",
    "club": "red-rose",
    "sex": "M",
    "ageCategory": "V60",
    "runnerId": 11922
  },
  {
    "id": 140,
    "firstName": "Brian",
    "lastName": "Dearnaley",
    "club": "preston",
    "sex": "M",
    "ageCategory": "V60",
    "runnerId": 12858
  },
  {
    "id": 141,
    "firstName": "Eileen",
    "lastName": "Bates",
    "club": "preston",
    "sex": "F",
    "ageCategory": "V60",
    "runnerId": 13115
  },
  {
    "id": 142,
    "firstName": "Joe",
    "lastName": "Howard",
    "club": "preston",
    "sex": "M",
    "ageCategory": "V60",
    "runnerId": 12428
  },
  {
    "id": 143,
    "firstName": "Roger",
    "lastName": "Johnson",
    "club": "red-rose",
    "sex": "M",
    "ageCategory": "V50",
    "runnerId": 11705
  },
  {
    "id": 144,
    "firstName": "Phil",
    "lastName": "McCullagh",
    "club": "chorley-ac",
    "sex": "M",
    "ageCategory": "V50",
    "runnerId": 12264
  },
  {
    "id": 145,
    "firstName": "Les",
    "lastName": "Paul",
    "club": "chorley-ac",
    "sex": "M",
    "ageCategory": "V60",
    "runnerId": 12526
  },
  {
    "id": 146,
    "firstName": "Tom",
    "lastName": "Hilton",
    "club": "chorley-ac",
    "sex": "M",
    "ageCategory": "V60",
    "runnerId": 12318
  },
  {
    "id": 147,
    "firstName": "Dawn",
    "lastName": "Lock",
    "club": "lytham",
    "sex": "F",
    "ageCategory": "V60",
    "runnerId": 11890
  },
  {
    "id": 148,
    "firstName": "Mike",
    "lastName": "Coppin",
    "club": "chorley-ac",
    "sex": "M",
    "ageCategory": "V60",
    "runnerId": 12531
  },
  {
    "id": 149,
    "firstName": "Lee",
    "lastName": "Barlow",
    "club": "wesham",
    "sex": "M",
    "ageCategory": "SEN",
    "runnerId": 10084
  },
  {
    "id": 150,
    "firstName": "Steve",
    "lastName": "Myerscough",
    "club": "wesham",
    "sex": "M",
    "ageCategory": "SEN",
    "runnerId": 10122
  },
  {
    "id": 151,
    "firstName": "John",
    "lastName": "Shepherd",
    "club": "red-rose",
    "sex": "M",
    "ageCategory": "V40",
    "runnerId": 10581
  },
  {
    "id": 152,
    "firstName": "Gary",
    "lastName": "Johnston",
    "club": "blackpool",
    "sex": "M",
    "ageCategory": "V50",
    "runnerId": 13140
  },
  {
    "id": 153,
    "firstName": "Mark",
    "lastName": "Belfield",
    "club": "wesham",
    "sex": "M",
    "ageCategory": "SEN",
    "runnerId": 10019
  },
  {
    "id": 154,
    "firstName": "Ken",
    "lastName": "Addison",
    "club": "red-rose",
    "sex": "M",
    "ageCategory": "V50",
    "runnerId": 11471
  },
  {
    "id": 155,
    "firstName": "Fred",
    "lastName": "Lynch",
    "club": "red-rose",
    "sex": "M",
    "ageCategory": "V50",
    "runnerId": 11782
  },
  {
    "id": 156,
    "firstName": "Paul",
    "lastName": "Woan",
    "club": "red-rose",
    "sex": "M",
    "ageCategory": "V40",
    "runnerId": 11692
  },
  {
    "id": 157,
    "firstName": "Anthony",
    "lastName": "Thornley",
    "club": "red-rose",
    "sex": "M",
    "ageCategory": "V40",
    "runnerId": 12929
  },
  {
    "id": 158,
    "firstName": "Cliff",
    "lastName": "Utting",
    "club": "red-rose",
    "sex": "M",
    "ageCategory": "V50",
    "runnerId": 12833
  },
  {
    "id": 159,
    "firstName": "Geof",
    "lastName": "Haworth",
    "club": "red-rose",
    "sex": "M",
    "ageCategory": "V40",
    "runnerId": 12927
  },
  {
    "id": 160,
    "firstName": "Billy",
    "lastName": "Johnstone",
    "club": "preston",
    "sex": "M",
    "ageCategory": "V40",
    "runnerId": 10635
  },
  {
    "id": 161,
    "firstName": "Helen",
    "lastName": "Lawrenson",
    "club": "wesham",
    "sex": "F",
    "ageCategory": "V40",
    "runnerId": 10181
  },
  {
    "id": 162,
    "firstName": "Alison",
    "lastName": "John-Haslam",
    "club": "red-rose",
    "sex": "F",
    "ageCategory": "V40",
    "runnerId": 12403
  },
  {
    "id": 163,
    "firstName": "David",
    "lastName": "Brooks",
    "club": "blackpool",
    "sex": "M",
    "ageCategory": "SEN",
    "runnerId": 13149
  },
  {
    "id": 164,
    "firstName": "Peter",
    "lastName": "Bartlett",
    "club": "wesham",
    "sex": "M",
    "ageCategory": "V60",
    "runnerId": 11540
  },
  {
    "id": 165,
    "firstName": "John",
    "lastName": "Sharples",
    "club": "wesham",
    "sex": "M",
    "ageCategory": "V50",
    "runnerId": 12838
  },
  {
    "id": 166,
    "firstName": "Steve",
    "lastName": "Quarmby",
    "club": "lytham",
    "sex": "M",
    "ageCategory": "V40",
    "runnerId": 12836
  },
  {
    "id": 167,
    "firstName": "Kevin",
    "lastName": "Ashworth",
    "club": "lytham",
    "sex": "M",
    "ageCategory": "V40",
    "runnerId": 12748
  },
  {
    "id": 168,
    "firstName": "Colin",
    "lastName": "Nelion",
    "club": "lytham",
    "sex": "M",
    "ageCategory": "SEN",
    "runnerId": 13975
  },
  {
    "id": 169,
    "firstName": "Janine",
    "lastName": "Needham",
    "club": "red-rose",
    "sex": "F",
    "ageCategory": "V35",
    "runnerId": 11085
  },
  {
    "id": 170,
    "firstName": "Mark",
    "lastName": "Haworth",
    "club": "red-rose",
    "sex": "M",
    "ageCategory": "SEN",
    "runnerId": 13020
  },
  {
    "id": 171,
    "firstName": "Jen",
    "lastName": "Salt",
    "club": "wesham",
    "sex": "F",
    "ageCategory": "V35",
    "runnerId": 10241
  },
  {
    "id": 172,
    "firstName": "Paula",
    "lastName": "Plowman",
    "club": "red-rose",
    "sex": "F",
    "ageCategory": "V45",
    "runnerId": 10297
  },
  {
    "id": 173,
    "firstName": "Lauren",
    "lastName": "Caton",
    "club": "chorley-ac",
    "sex": "F",
    "ageCategory": "SEN",
    "runnerId": 13201
  },
  {
    "id": 174,
    "firstName": "Eddie",
    "lastName": "Stewart",
    "club": "preston",
    "sex": "M",
    "ageCategory": "V60",
    "runnerId": 12388
  },
  {
    "id": 175,
    "firstName": "Laura",
    "lastName": "Ashworth",
    "club": "lytham",
    "sex": "F",
    "ageCategory": "V35",
    "runnerId": 12720
  },
  {
    "id": 176,
    "firstName": "Debbie",
    "lastName": "Kirkham",
    "club": "red-rose",
    "sex": "F",
    "ageCategory": "V40",
    "runnerId": 13976
  },
  {
    "id": 177,
    "firstName": "Bec",
    "lastName": "Willetts",
    "club": "lytham",
    "sex": "F",
    "ageCategory": "V40",
    "runnerId": 12727
  },
  {
    "id": 178,
    "firstName": "David",
    "lastName": "Roberts",
    "club": "preston",
    "sex": "M",
    "ageCategory": "V60",
    "runnerId": 11873
  },
  {
    "id": 179,
    "firstName": "Pamela",
    "lastName": "Hardman",
    "club": "lytham",
    "sex": "F",
    "ageCategory": "V50",
    "runnerId": 11433
  },
  {
    "id": 180,
    "firstName": "Melanie",
    "lastName": "Howorth",
    "club": "preston",
    "sex": "F",
    "ageCategory": "V35",
    "runnerId": 13977
  },
  {
    "id": 181,
    "firstName": "Karen",
    "lastName": "Woan",
    "club": "red-rose",
    "sex": "F",
    "ageCategory": "V35",
    "runnerId": 13114
  },
  {
    "id": 182,
    "firstName": "Jon",
    "lastName": "Green",
    "club": "preston",
    "sex": "M",
    "ageCategory": "SEN",
    "runnerId": 13544
  },
  {
    "id": 183,
    "firstName": "Philip",
    "lastName": "Bulter",
    "club": "red-rose",
    "sex": "M",
    "ageCategory": "V40",
    "runnerId": 13978
  },
  {
    "id": 184,
    "firstName": "John",
    "lastName": "Hyde",
    "club": "red-rose",
    "sex": "M",
    "ageCategory": "V50",
    "runnerId": 11026
  },
  {
    "id": 185,
    "firstName": "Colin",
    "lastName": "Nelson",
    "club": "lytham",
    "sex": "M",
    "ageCategory": "SEN",
    "runnerId": 12991
  },
  {
    "id": 186,
    "firstName": "Alistair",
    "lastName": "Morris",
    "club": "wesham",
    "sex": "M",
    "ageCategory": "V50",
    "runnerId": 12256
  },
  {
    "id": 187,
    "firstName": "Dave",
    "lastName": "Earnshaw",
    "club": "red-rose",
    "sex": "M",
    "ageCategory": "V50",
    "runnerId": 13401
  },
  {
    "id": 188,
    "firstName": "Kath",
    "lastName": "Hoyer",
    "club": "wesham",
    "sex": "F",
    "ageCategory": "V50",
    "runnerId": 12290
  },
  {
    "id": 189,
    "firstName": "Bernard",
    "lastName": "Elkington",
    "club": "red-rose",
    "sex": "M",
    "ageCategory": "V70",
    "runnerId": 12201
  },
  {
    "id": 190,
    "firstName": "Sam",
    "lastName": "Banner",
    "club": "lytham",
    "sex": "M",
    "ageCategory": "JUN",
    "runnerId": 12820
  },
  {
    "id": 191,
    "firstName": "Mick",
    "lastName": "McLoughlin",
    "club": "preston",
    "sex": "M",
    "ageCategory": "V50",
    "runnerId": 10861
  },
  {
    "id": 192,
    "firstName": "Jim",
    "lastName": "Doherty",
    "club": "preston",
    "sex": "M",
    "ageCategory": "V40",
    "runnerId": 11429
  },
  {
    "id": 193,
    "firstName": "Steven",
    "lastName": "Jackson",
    "club": "preston",
    "sex": "M",
    "ageCategory": "V50",
    "runnerId": 12078
  },
  {
    "id": 194,
    "firstName": "Peter",
    "lastName": "Carter",
    "club": "preston",
    "sex": "M",
    "ageCategory": "V40",
    "runnerId": 12003
  },
  {
    "id": 195,
    "firstName": "Debbie",
    "lastName": "Kirkman",
    "club": "red-rose",
    "sex": "F",
    "ageCategory": "V40",
    "runnerId": 12830
  },
  {
    "id": 196,
    "firstName": "Julia",
    "lastName": "Rolfe",
    "club": "lytham",
    "sex": "F",
    "ageCategory": "V40",
    "runnerId": 10663
  },
  {
    "id": 197,
    "firstName": "Alan",
    "lastName": "Raby",
    "club": "preston",
    "sex": "M",
    "ageCategory": "SEN",
    "runnerId": 12939
  },
  {
    "id": 198,
    "firstName": "Tony",
    "lastName": "Rudd",
    "club": "lytham",
    "sex": "M",
    "ageCategory": "SEN",
    "runnerId": 13123
  },
  {
    "id": 199,
    "firstName": "Emma",
    "lastName": "Cowie-Shaw",
    "club": "red-rose",
    "sex": "F",
    "ageCategory": "SEN",
    "runnerId": 13022
  },
  {
    "id": 200,
    "firstName": "Eileen",
    "lastName": "Dearnaley",
    "club": "preston",
    "sex": "F",
    "ageCategory": "V60",
    "runnerId": 12735
  }
]
